okta_awsauth-0.9.4.data/data/__init__.py
okta_awsauth-0.9.4.data/data/aws_auth.py
okta_awsauth-0.9.4.data/data/okta_auth.py
okta_awsauth-0.9.4.data/data/okta_auth_config.py
okta_awsauth-0.9.4.data/data/version.py
oktaauth/__init__.py
oktaauth/aws_auth.py
oktaauth/okta_auth.py
oktaauth/okta_auth_config.py
oktaauth/okta_awscli.py
oktaauth/version.py
okta_awsauth-0.9.4.dist-info/LICENSE
okta_awsauth-0.9.4.dist-info/METADATA
okta_awsauth-0.9.4.dist-info/WHEEL
okta_awsauth-0.9.4.dist-info/entry_points.txt
okta_awsauth-0.9.4.dist-info/top_level.txt
okta_awsauth-0.9.4.dist-info/RECORD
